{"hash":"a9bd125ee674ae744df89927c73b8058732177c1","data":{"allGoogleSheet":{"edges":[{"node":{"id":"2","title":"Forever Freedom","subtitle":"Orange Flaroved Aloe Vera Juice","imgOne":"forever-freedom.jpg","link":"http://flpshop.rs/napici/11619/forever-freedom.html","textOne":"Započnite svoj dan na praktičan i hranljiv način uz Forever Freedom!"}},{"node":{"id":"1","title":"Aloa vera gel","subtitle":"Forever Aloea Vera Gel","imgOne":"aloja_1.jpg","link":"http://flpshop.rs/napici/11837/forever-aloe-vera-gel.html","textOne":"99,7% cista aloja veza za Vas imuni sistem"}}]}},"context":{}}